{
  "neck": [
    {
      "code": 1,
      "name_kor": "블루 엔젤릭브로치",
      "name_eng": "Blue Angelic Brooch",
      "rarity": 0,
      "sell_price": 100000,
      "icon": 14,
      "shape": "0402",
      "shape_alpha": "c",
      "req_lv": 1
    },
    {
      "code": 2,
      "name_kor": "블루 엔젤릭브로치",
      "name_eng": "Blue Angelic Brooch",
      "rarity": 0,
      "sell_price": 100000,
      "icon": 14,
      "shape": "0402",
      "shape_alpha": "c",
      "req_lv": 1
    },
    {
      "code": 3,
      "name_kor": "동제 고딕브로치",
      "name_eng": "Copper Gothic Brooch",
      "rarity": 0,
      "sell_price": 100000,
      "icon": 45,
      "shape": "1101",
      "shape_alpha": "a",
      "req_lv": 1
    },
    {
      "code": 4,
      "name_kor": "골드 엔젤릭브로치",
      "name_eng": "Gold Angelic Brooch",
      "rarity": 0,
      "sell_price": 100000,
      "icon": 13,
      "shape": "0401",
      "shape_alpha": "c",
      "req_lv": 1
    },
    {
      "code": 5,
      "name_kor": "골드 엔젤릭브로치",
      "name_eng": "Gold Angelic Brooch",
      "rarity": 0,
      "sell_price": 100000,
      "icon": 13,
      "shape": "0401",
      "shape_alpha": "c",
      "req_lv": 1
    },
    {
      "code": 6,
      "name_kor": "금제 고딕브로치",
      "name_eng": "Golden Gothic Brooch",
      "rarity": 0,
      "sell_price": 100000,
      "icon": 46,
      "shape": "1102",
      "shape_alpha": "a",
      "req_lv": 1
    },
    {
      "code": 7,
      "name_kor": "철제 고딕브로치",
      "name_eng": "Iron Gothic Brooch",
      "rarity": 0,
      "sell_price": 100000,
      "icon": 47,
      "shape": "1103",
      "shape_alpha": "a",
      "req_lv": 1
    },
    {
      "code": 8,
      "name_kor": "레드 엔젤릭브로치",
      "name_eng": "Red Angelic Brooch",
      "rarity": 0,
      "sell_price": 100000,
      "icon": 15,
      "shape": "0403",
      "shape_alpha": "c",
      "req_lv": 1
    },
    {
      "code": 9,
      "name_kor": "레드 엔젤릭브로치",
      "name_eng": "Red Angelic Brooch",
      "rarity": 0,
      "sell_price": 100000,
      "icon": 15,
      "shape": "0403",
      "shape_alpha": "c",
      "req_lv": 1
    },
    {
      "code": 10,
      "name_kor": "실버 엔젤릭브로치",
      "name_eng": "Silver Angelic Brooch",
      "rarity": 0,
      "sell_price": 100000,
      "icon": 12,
      "shape": "0400",
      "shape_alpha": "c",
      "req_lv": 1
    },
    {
      "code": 11,
      "name_kor": "실버 엔젤릭브로치",
      "name_eng": "Silver Angelic Brooch",
      "rarity": 0,
      "sell_price": 100000,
      "icon": 12,
      "shape": "0400",
      "shape_alpha": "c",
      "req_lv": 1
    },
    {
      "code": 12,
      "name_kor": "은제 고딕브로치",
      "name_eng": "Silver Gothic Brooch",
      "rarity": 0,
      "sell_price": 100000,
      "icon": 44,
      "shape": "1100",
      "shape_alpha": "a",
      "req_lv": 1
    },
    {
      "code": 13,
      "name_kor": "붉은색 봇짐",
      "name_eng": "Red Bundle",
      "rarity": 0,
      "sell_price": 100000,
      "icon": 41,
      "shape": "1201",
      "shape_alpha": "cd",
      "req_lv": 1
    },
    {
      "code": 14,
      "name_kor": "검은색 봇짐",
      "name_eng": "Black Bundle",
      "rarity": 0,
      "sell_price": 100000,
      "icon": 43,
      "shape": "1203",
      "shape_alpha": "cd",
      "req_lv": 1
    },
    {
      "code": 15,
      "name_kor": "암청색 봇짐",
      "name_eng": "Cobalt Bundle",
      "rarity": 0,
      "sell_price": 100000,
      "icon": 42,
      "shape": "1202",
      "shape_alpha": "cd",
      "req_lv": 1
    },
    {
      "code": 16,
      "name_kor": "흰색 봇짐",
      "name_eng": "White Bundle",
      "rarity": 0,
      "sell_price": 100000,
      "icon": 40,
      "shape": "1200",
      "shape_alpha": "cd",
      "req_lv": 1
    },
    {
      "code": 17,
      "name_kor": "검은장미 코사지",
      "name_eng": "Black Rose Corsage",
      "rarity": 0,
      "sell_price": 100000,
      "icon": 57,
      "shape": "1601",
      "shape_alpha": "a",
      "req_lv": 1
    },
    {
      "code": 18,
      "name_kor": "붉은장미 코사지",
      "name_eng": "Red Rose Corsage",
      "rarity": 0,
      "sell_price": 100000,
      "icon": 58,
      "shape": "1602",
      "shape_alpha": "a",
      "req_lv": 1
    },
    {
      "code": 19,
      "name_kor": "흰장미 코사지",
      "name_eng": "White Rose Corsage",
      "rarity": 0,
      "sell_price": 100000,
      "icon": 56,
      "shape": "1600",
      "shape_alpha": "a",
      "req_lv": 1
    },
    {
      "code": 20,
      "name_kor": "노란장미 코사지",
      "name_eng": "Yellow Rose Corsage",
      "rarity": 0,
      "sell_price": 100000,
      "icon": 59,
      "shape": "1603",
      "shape_alpha": "a",
      "req_lv": 1
    },
    {
      "code": 21,
      "name_kor": "청동 체인장식",
      "name_eng": "Bronze Chain Decoration",
      "rarity": 2,
      "sell_price": 1000000,
      "icon": 23,
      "shape": "0603",
      "shape_alpha": "c",
      "req_lv": 30
    },
    {
      "code": 22,
      "name_kor": "금 체인장식",
      "name_eng": "Gold Chain Decoration",
      "rarity": 2,
      "sell_price": 1000000,
      "icon": 21,
      "shape": "0601",
      "shape_alpha": "c",
      "req_lv": 30
    },
    {
      "code": 23,
      "name_kor": "강철 체인장식",
      "name_eng": "Steel Chain Decoration",
      "rarity": 2,
      "sell_price": 1000000,
      "icon": 22,
      "shape": "0602",
      "shape_alpha": "c",
      "req_lv": 30
    },
    {
      "code": 24,
      "name_kor": "은 체인장식",
      "name_eng": "Silver Chain Decoration",
      "rarity": 2,
      "sell_price": 1000000,
      "icon": 20,
      "shape": "0600",
      "shape_alpha": "c",
      "req_lv": 30
    },
    {
      "code": 25,
      "name_kor": "블랙크로우 깃털망토",
      "name_eng": "Black Craw Feathers Cloak",
      "rarity": 2,
      "sell_price": 1000000,
      "icon": 60,
      "shape": "1800",
      "shape_alpha": "cd",
      "req_lv": 30
    },
    {
      "code": 26,
      "name_kor": "검은색 망사탑",
      "name_eng": "Black Gauze Top",
      "rarity": 0,
      "sell_price": 100000,
      "icon": 8,
      "shape": "0200",
      "shape_alpha": "d",
      "req_lv": 1
    },
    {
      "code": 27,
      "name_kor": "진청색 망사탑",
      "name_eng": "Deep Blue Gauze Top",
      "rarity": 0,
      "sell_price": 100000,
      "icon": 10,
      "shape": "0202",
      "shape_alpha": "d",
      "req_lv": 1
    },
    {
      "code": 28,
      "name_kor": "회색 망사탑",
      "name_eng": "Gray Gauze Top",
      "rarity": 0,
      "sell_price": 100000,
      "icon": 11,
      "shape": "0203",
      "shape_alpha": "d",
      "req_lv": 1
    },
    {
      "code": 29,
      "name_kor": "붉은색 망사탑",
      "name_eng": "Red Gauze Top",
      "rarity": 0,
      "sell_price": 100000,
      "icon": 9,
      "shape": "0201",
      "shape_alpha": "d",
      "req_lv": 1
    },
    {
      "code": 30,
      "name_kor": "검은색 카니발망토",
      "name_eng": "Black Carnival Manteau",
      "rarity": 0,
      "sell_price": 100000,
      "icon": 35,
      "shape": "0903",
      "shape_alpha": "bc",
      "req_lv": 1
    },
    {
      "code": 31,
      "name_kor": "푸른색 카니발망토",
      "name_eng": "Blue Carnival Manteau",
      "rarity": 0,
      "sell_price": 100000,
      "icon": 34,
      "shape": "0902",
      "shape_alpha": "bc",
      "req_lv": 1
    },
    {
      "code": 32,
      "name_kor": "금색 카니발망토",
      "name_eng": "Gold Carnival Manteau",
      "rarity": 0,
      "sell_price": 100000,
      "icon": 33,
      "shape": "0901",
      "shape_alpha": "bc",
      "req_lv": 1
    },
    {
      "code": 33,
      "name_kor": "흰색 카니발망토",
      "name_eng": "White Carnival Manteau",
      "rarity": 0,
      "sell_price": 100000,
      "icon": 32,
      "shape": "0900",
      "shape_alpha": "bc",
      "req_lv": 1
    },
    {
      "code": 34,
      "name_kor": "검은색 머플러",
      "name_eng": "Black Muffler",
      "rarity": 0,
      "sell_price": 100000,
      "icon": 38,
      "shape": "0302",
      "shape_alpha": "cd",
      "req_lv": 1
    },
    {
      "code": 35,
      "name_kor": "보라색 머플러",
      "name_eng": "Purple Muffler",
      "rarity": 0,
      "sell_price": 100000,
      "icon": 37,
      "shape": "0301",
      "shape_alpha": "cd",
      "req_lv": 1
    },
    {
      "code": 36,
      "name_kor": "붉은색 머플러",
      "name_eng": "Red Muffler",
      "rarity": 0,
      "sell_price": 100000,
      "icon": 36,
      "shape": "0300",
      "shape_alpha": "cd",
      "req_lv": 1
    },
    {
      "code": 37,
      "name_kor": "흰색 머플러",
      "name_eng": "White Muffler",
      "rarity": 0,
      "sell_price": 100000,
      "icon": 39,
      "shape": "0303",
      "shape_alpha": "cd",
      "req_lv": 1
    },
    {
      "code": 38,
      "name_kor": "붉은색 체크 목도리",
      "name_eng": "Red Check Muffler",
      "rarity": 0,
      "sell_price": 100000,
      "icon": 61,
      "shape": "1500",
      "shape_alpha": "acd",
      "req_lv": 1
    },
    {
      "code": 39,
      "name_kor": "흰색 체크 목도리",
      "name_eng": "White Check Muffler",
      "rarity": 0,
      "sell_price": 100000,
      "icon": 63,
      "shape": "1502",
      "shape_alpha": "acd",
      "req_lv": 1
    },
    {
      "code": 40,
      "name_kor": "노란색 체크 목도리",
      "name_eng": "Yellow Check Muffler",
      "rarity": 0,
      "sell_price": 100000,
      "icon": 62,
      "shape": "1501",
      "shape_alpha": "acd",
      "req_lv": 1
    },
    {
      "code": 41,
      "name_kor": "연두색 체크 목도리",
      "name_eng": "Yellowish Green Check Muffler",
      "rarity": 0,
      "sell_price": 100000,
      "icon": 64,
      "shape": "1503",
      "shape_alpha": "acd",
      "req_lv": 1
    },
    {
      "code": 42,
      "name_kor": "청록색 염주목걸이",
      "name_eng": "BluishGreen Rosary Necklace",
      "rarity": 0,
      "sell_price": 100000,
      "icon": 29,
      "shape": "0801",
      "shape_alpha": "c",
      "req_lv": 1
    },
    {
      "code": 43,
      "name_kor": "파란가죽끈목걸이",
      "name_eng": "Blue Leather Necklace",
      "rarity": 0,
      "sell_price": 100000,
      "icon": 7,
      "shape": "0103",
      "shape_alpha": "d",
      "req_lv": 1
    },
    {
      "code": 44,
      "name_kor": "구리 십자목걸이",
      "name_eng": "Copper Cross Necklace",
      "rarity": 0,
      "sell_price": 100000,
      "icon": 19,
      "shape": "0503",
      "shape_alpha": "c",
      "req_lv": 1
    },
    {
      "code": 45,
      "name_kor": "구리 십자목걸이",
      "name_eng": "Copper Cross Necklace",
      "rarity": 0,
      "sell_price": 100000,
      "icon": 19,
      "shape": "0503",
      "shape_alpha": "c",
      "req_lv": 1
    },
    {
      "code": 46,
      "name_kor": "암적색 염주목걸이",
      "name_eng": "DarkRed Rosary Necklace",
      "rarity": 0,
      "sell_price": 100000,
      "icon": 30,
      "shape": "0802",
      "shape_alpha": "c",
      "req_lv": 1
    },
    {
      "code": 47,
      "name_kor": "황금 십자목걸이",
      "name_eng": "Gold Cross Necklace",
      "rarity": 0,
      "sell_price": 100000,
      "icon": 16,
      "shape": "0500",
      "shape_alpha": "c",
      "req_lv": 1
    },
    {
      "code": 48,
      "name_kor": "황금 십자목걸이",
      "name_eng": "Gold Cross Necklace",
      "rarity": 0,
      "sell_price": 100000,
      "icon": 16,
      "shape": "0500",
      "shape_alpha": "c",
      "req_lv": 1
    },
    {
      "code": 49,
      "name_kor": "황금색 염주목걸이",
      "name_eng": "Gold Rosary Necklace",
      "rarity": 0,
      "sell_price": 100000,
      "icon": 31,
      "shape": "0803",
      "shape_alpha": "c",
      "req_lv": 1
    },
    {
      "code": 50,
      "name_kor": "회색가죽끈목걸이",
      "name_eng": "Gray Leather Necklace",
      "rarity": 0,
      "sell_price": 100000,
      "icon": 6,
      "shape": "0102",
      "shape_alpha": "d",
      "req_lv": 1
    },
    {
      "code": 51,
      "name_kor": "가죽끈목걸이",
      "name_eng": "Leather Necklace",
      "rarity": 0,
      "sell_price": 100000,
      "icon": 4,
      "shape": "0100",
      "shape_alpha": "d",
      "req_lv": 1
    },
    {
      "code": 52,
      "name_kor": "보라색 염주목걸이",
      "name_eng": "Purple Rosary Necklace",
      "rarity": 0,
      "sell_price": 100000,
      "icon": 28,
      "shape": "0800",
      "shape_alpha": "c",
      "req_lv": 1
    },
    {
      "code": 53,
      "name_kor": "붉은가죽끈목걸이",
      "name_eng": "Red Leather Necklace",
      "rarity": 0,
      "sell_price": 100000,
      "icon": 5,
      "shape": "0101",
      "shape_alpha": "d",
      "req_lv": 1
    },
    {
      "code": 54,
      "name_kor": "강철 십자목걸이",
      "name_eng": "Steel Cross Necklace",
      "rarity": 0,
      "sell_price": 100000,
      "icon": 18,
      "shape": "0502",
      "shape_alpha": "c",
      "req_lv": 1
    },
    {
      "code": 55,
      "name_kor": "강철 십자목걸이",
      "name_eng": "Steel Cross Necklace",
      "rarity": 0,
      "sell_price": 100000,
      "icon": 18,
      "shape": "0502",
      "shape_alpha": "c",
      "req_lv": 1
    },
    {
      "code": 56,
      "name_kor": "은 십자목걸이",
      "name_eng": "Silver Cross Necklace",
      "rarity": 0,
      "sell_price": 100000,
      "icon": 17,
      "shape": "0501",
      "shape_alpha": "c",
      "req_lv": 1
    },
    {
      "code": 57,
      "name_kor": "은 십자목걸이",
      "name_eng": "Silver Cross Necklace",
      "rarity": 0,
      "sell_price": 100000,
      "icon": 17,
      "shape": "0501",
      "shape_alpha": "c",
      "req_lv": 1
    },
    {
      "code": 58,
      "name_kor": "까마귀 깃털장식",
      "name_eng": "Crow Feather Ornamentation",
      "rarity": 0,
      "sell_price": 100000,
      "icon": 48,
      "shape": "1300",
      "shape_alpha": "cd",
      "req_lv": 1
    },
    {
      "code": 59,
      "name_kor": "홍학 깃털장식",
      "name_eng": "Flamingo Feather Ornamentation",
      "rarity": 0,
      "sell_price": 100000,
      "icon": 51,
      "shape": "1303",
      "shape_alpha": "cd",
      "req_lv": 1
    },
    {
      "code": 60,
      "name_kor": "황조롱이 깃털장식",
      "name_eng": "Kestrel Feather Ornamentation",
      "rarity": 0,
      "sell_price": 100000,
      "icon": 50,
      "shape": "1302",
      "shape_alpha": "cd",
      "req_lv": 1
    },
    {
      "code": 61,
      "name_kor": "백조 깃털장식",
      "name_eng": "Swan Feather Ornamentation",
      "rarity": 0,
      "sell_price": 100000,
      "icon": 49,
      "shape": "1301",
      "shape_alpha": "cd",
      "req_lv": 1
    },
    {
      "code": 62,
      "name_kor": "검은색 폴라나시",
      "name_eng": "Black Pola Sleeveless",
      "rarity": 0,
      "sell_price": 100000,
      "icon": 52,
      "shape": "1400",
      "shape_alpha": "b",
      "req_lv": 1
    },
    {
      "code": 63,
      "name_kor": "푸른색 폴라나시",
      "name_eng": "Blue Pola Sleeveless",
      "rarity": 0,
      "sell_price": 100000,
      "icon": 55,
      "shape": "1403",
      "shape_alpha": "b",
      "req_lv": 1
    },
    {
      "code": 64,
      "name_kor": "녹색 폴라나시",
      "name_eng": "Green Pola Sleeveless",
      "rarity": 0,
      "sell_price": 100000,
      "icon": 54,
      "shape": "1402",
      "shape_alpha": "b",
      "req_lv": 1
    },
    {
      "code": 65,
      "name_kor": "붉은색 폴라나시",
      "name_eng": "Red Pola Sleeveless",
      "rarity": 0,
      "sell_price": 100000,
      "icon": 53,
      "shape": "1401",
      "shape_alpha": "b",
      "req_lv": 1
    },
    {
      "code": 66,
      "name_kor": "검은색 우쿨렐레",
      "name_eng": "Black  Ukulele",
      "rarity": 0,
      "sell_price": 100000,
      "icon": 27,
      "shape": "0703",
      "shape_alpha": "bc",
      "req_lv": 1
    },
    {
      "code": 67,
      "name_kor": "푸른색 우쿨렐레",
      "name_eng": "Blue  Ukulele",
      "rarity": 0,
      "sell_price": 100000,
      "icon": 26,
      "shape": "0702",
      "shape_alpha": "bc",
      "req_lv": 1
    },
    {
      "code": 68,
      "name_kor": "갈색 우쿨렐레",
      "name_eng": "Brown  Ukulele",
      "rarity": 0,
      "sell_price": 100000,
      "icon": 24,
      "shape": "0700",
      "shape_alpha": "bc",
      "req_lv": 1
    },
    {
      "code": 69,
      "name_kor": "흰색 우쿨렐레",
      "name_eng": "White  Ukulele",
      "rarity": 0,
      "sell_price": 100000,
      "icon": 25,
      "shape": "0701",
      "shape_alpha": "bc",
      "req_lv": 1
    },
    {
      "code": 70,
      "name_kor": "크림슨 고딕타투",
      "name_eng": "Crimson Gothic Tattoo",
      "rarity": 0,
      "sell_price": 100000,
      "icon": 2,
      "shape": "0002",
      "shape_alpha": "d",
      "req_lv": 1
    },
    {
      "code": 71,
      "name_kor": "포레스트 고딕타투",
      "name_eng": "Forest Gothic Tattoo",
      "rarity": 0,
      "sell_price": 100000,
      "icon": 3,
      "shape": "0003",
      "shape_alpha": "d",
      "req_lv": 1
    },
    {
      "code": 72,
      "name_kor": "고딕타투",
      "name_eng": "Gothic Tattoo",
      "rarity": 0,
      "sell_price": 100000,
      "icon": 0,
      "shape": "0000",
      "shape_alpha": "d",
      "req_lv": 1
    },
    {
      "code": 73,
      "name_kor": "페일 고딕타투",
      "name_eng": "Pale Gothic Tattoo",
      "rarity": 0,
      "sell_price": 100000,
      "icon": 1,
      "shape": "0001",
      "shape_alpha": "d",
      "req_lv": 1
    }
  ]
}